[{"engineId": 10, "t": 1, "rul": 5.56, "anomRaw": 0.0, "anomSmooth": 0.0, "anomState": "OFF", "label": "Planned Maintenance", "reasonCodes": "RUL_LOW|ANOM_OFF", "reasonText": "RUL <= theta; planlı bakım penceresine girildi.", "action": "Planlı bakım/inspection", "theta": 30.0, "alphaHigh": 0.2692, "alphaLow": 0.2423, "policyVersion": "v2", "runId": "ds-20260211T154144Z-814aa2e321"}, {"engineId": 10, "t": 2, "rul": 52.19, "anomRaw": 0.007448, "anomSmooth": 0.001862, "anomState": "OFF", "label": "Normal Operation", "reasonCodes": "RUL_HIGH|ANOM_OFF", "reasonText": "RUL > theta ve anomaly_state OFF; rutin operasyon devam.", "action": "Rutin izleme", "theta": 30.0, "alphaHigh": 0.2692, "alphaLow": 0.2423, "policyVersion": "v2", "runId": "ds-20260211T154144Z-814aa2e321"}, {"engineId": 10, "t": 3, "rul": 0.0, "anomRaw": 0.000486, "anomSmooth": 0.001518, "anomState": "OFF", "label": "Planned Maintenance", "reasonCodes": "RUL_LOW|ANOM_OFF", "reasonText": "RUL <= theta; planlı bakım penceresine girildi.", "action": "Planlı bakım/inspection", "theta": 30.0, "alphaHigh": 0.2692, "alphaLow": 0.2423, "policyVersion": "v2", "runId": "ds-20260211T154144Z-814aa2e321"}, {"engineId": 10, "t": 4, "rul": 10.99, "anomRaw": 3e-06, "anomSmooth": 0.001139, "anomState": "OFF", "label": "Planned Maintenance", "reasonCodes": "RUL_LOW|ANOM_OFF", "reasonText": "RUL <= theta; planlı bakım penceresine girildi.", "action": "Planlı bakım/inspection", "theta": 30.0, "alphaHigh": 0.2692, "alphaLow": 0.2423, "policyVersion": "v2", "runId": "ds-20260211T154144Z-814aa2e321"}, {"engineId": 10, "t": 5, "rul": 11.8, "anomRaw": 0.0, "anomSmooth": 0.000854, "anomState": "OFF", "label": "Planned Maintenance", "reasonCodes": "RUL_LOW|ANOM_OFF", "reasonText": "RUL <= theta; planlı bakım penceresine girildi.", "action": "Planlı bakım/inspection", "theta": 30.0, "alphaHigh": 0.2692, "alphaLow": 0.2423, "policyVersion": "v2", "runId": "ds-20260211T154144Z-814aa2e321"}, {"engineId": 10, "t": 6, "rul": 0.0, "anomRaw": 0.002334, "anomSmooth": 0.001224, "anomState": "OFF", "label": "Planned Maintenance", "reasonCodes": "RUL_LOW|ANOM_OFF", "reasonText": "RUL <= theta; planlı bakım penceresine girildi.", "action": "Planlı bakım/inspection", "theta": 30.0, "alphaHigh": 0.2692, "alphaLow": 0.2423, "policyVersion": "v2", "runId": "ds-20260211T154144Z-814aa2e321"}, {"engineId": 10, "t": 7, "rul": 0.0, "anomRaw": 1.1e-05, "anomSmooth": 0.000921, "anomState": "OFF", "label": "Planned Maintenance", "reasonCodes": "RUL_LOW|ANOM_OFF", "reasonText": "RUL <= theta; planlı bakım penceresine girildi.", "action": "Planlı bakım/inspection", "theta": 30.0, "alphaHigh": 0.2692, "alphaLow": 0.2423, "policyVersion": "v2", "runId": "ds-20260211T154144Z-814aa2e321"}, {"engineId": 10, "t": 8, "rul": 53.2, "anomRaw": 0.003856, "anomSmooth": 0.001655, "anomState": "OFF", "label": "Normal Operation", "reasonCodes": "RUL_HIGH|ANOM_OFF", "reasonText": "RUL > theta ve anomaly_state OFF; rutin operasyon devam.", "action": "Rutin izleme", "theta": 30.0, "alphaHigh": 0.2692, "alphaLow": 0.2423, "policyVersion": "v2", "runId": "ds-20260211T154144Z-814aa2e321"}, {"engineId": 10, "t": 9, "rul": 0.0, "anomRaw": 0.999986, "anomSmooth": 0.251237, "anomState": "OFF", "label": "Planned Maintenance", "reasonCodes": "RUL_LOW|ANOM_OFF", "reasonText": "RUL <= theta; planlı bakım penceresine girildi.", "action": "Planlı bakım/inspection", "theta": 30.0, "alphaHigh": 0.2692, "alphaLow": 0.2423, "policyVersion": "v2", "runId": "ds-20260211T154144Z-814aa2e321"}, {"engineId": 10, "t": 10, "rul": 32.96, "anomRaw": 0.014383, "anomSmooth": 0.192024, "anomState": "OFF", "label": "Normal Operation", "reasonCodes": "RUL_HIGH|ANOM_OFF", "reasonText": "RUL > theta ve anomaly_state OFF; rutin operasyon devam.", "action": "Rutin izleme", "theta": 30.0, "alphaHigh": 0.2692, "alphaLow": 0.2423, "policyVersion": "v2", "runId": "ds-20260211T154144Z-814aa2e321"}, {"engineId": 10, "t": 11, "rul": 0.0, "anomRaw": 0.005995, "anomSmooth": 0.145517, "anomState": "OFF", "label": "Planned Maintenance", "reasonCodes": "RUL_LOW|ANOM_OFF", "reasonText": "RUL <= theta; planlı bakım penceresine girildi.", "action": "Planlı bakım/inspection", "theta": 30.0, "alphaHigh": 0.2692, "alphaLow": 0.2423, "policyVersion": "v2", "runId": "ds-20260211T154144Z-814aa2e321"}, {"engineId": 10, "t": 12, "rul": 0.0, "anomRaw": 0.001425, "anomSmooth": 0.109494, "anomState": "OFF", "label": "Planned Maintenance", "reasonCodes": "RUL_LOW|ANOM_OFF", "reasonText": "RUL <= theta; planlı bakım penceresine girildi.", "action": "Planlı bakım/inspection", "theta": 30.0, "alphaHigh": 0.2692, "alphaLow": 0.2423, "policyVersion": "v2", "runId": "ds-20260211T154144Z-814aa2e321"}, {"engineId": 10, "t": 13, "rul": 8.61, "anomRaw": 2.5e-05, "anomSmooth": 0.082127, "anomState": "OFF", "label": "Planned Maintenance", "reasonCodes": "RUL_LOW|ANOM_OFF", "reasonText": "RUL <= theta; planlı bakım penceresine girildi.", "action": "Planlı bakım/inspection", "theta": 30.0, "alphaHigh": 0.2692, "alphaLow": 0.2423, "policyVersion": "v2", "runId": "ds-20260211T154144Z-814aa2e321"}, {"engineId": 10, "t": 14, "rul": 0.0, "anomRaw": 1e-05, "anomSmooth": 0.061597, "anomState": "OFF", "label": "Planned Maintenance", "reasonCodes": "RUL_LOW|ANOM_OFF", "reasonText": "RUL <= theta; planlı bakım penceresine girildi.", "action": "Planlı bakım/inspection", "theta": 30.0, "alphaHigh": 0.2692, "alphaLow": 0.2423, "policyVersion": "v2", "runId": "ds-20260211T154144Z-814aa2e321"}, {"engineId": 10, "t": 15, "rul": 0.0, "anomRaw": 0.0, "anomSmooth": 0.046198, "anomState": "OFF", "label": "Planned Maintenance", "reasonCodes": "RUL_LOW|ANOM_OFF", "reasonText": "RUL <= theta; planlı bakım penceresine girildi.", "action": "Planlı bakım/inspection", "theta": 30.0, "alphaHigh": 0.2692, "alphaLow": 0.2423, "policyVersion": "v2", "runId": "ds-20260211T154144Z-814aa2e321"}, {"engineId": 10, "t": 16, "rul": 58.7, "anomRaw": 0.0, "anomSmooth": 0.034649, "anomState": "OFF", "label": "Normal Operation", "reasonCodes": "RUL_HIGH|ANOM_OFF", "reasonText": "RUL > theta ve anomaly_state OFF; rutin operasyon devam.", "action": "Rutin izleme", "theta": 30.0, "alphaHigh": 0.2692, "alphaLow": 0.2423, "policyVersion": "v2", "runId": "ds-20260211T154144Z-814aa2e321"}, {"engineId": 10, "t": 17, "rul": 56.88, "anomRaw": 0.0, "anomSmooth": 0.025986, "anomState": "OFF", "label": "Normal Operation", "reasonCodes": "RUL_HIGH|ANOM_OFF", "reasonText": "RUL > theta ve anomaly_state OFF; rutin operasyon devam.", "action": "Rutin izleme", "theta": 30.0, "alphaHigh": 0.2692, "alphaLow": 0.2423, "policyVersion": "v2", "runId": "ds-20260211T154144Z-814aa2e321"}, {"engineId": 10, "t": 18, "rul": 0.0, "anomRaw": 0.036814, "anomSmooth": 0.028693, "anomState": "OFF", "label": "Planned Maintenance", "reasonCodes": "RUL_LOW|ANOM_OFF", "reasonText": "RUL <= theta; planlı bakım penceresine girildi.", "action": "Planlı bakım/inspection", "theta": 30.0, "alphaHigh": 0.2692, "alphaLow": 0.2423, "policyVersion": "v2", "runId": "ds-20260211T154144Z-814aa2e321"}, {"engineId": 10, "t": 19, "rul": 31.86, "anomRaw": 0.0, "anomSmooth": 0.02152, "anomState": "OFF", "label": "Normal Operation", "reasonCodes": "RUL_HIGH|ANOM_OFF", "reasonText": "RUL > theta ve anomaly_state OFF; rutin operasyon devam.", "action": "Rutin izleme", "theta": 30.0, "alphaHigh": 0.2692, "alphaLow": 0.2423, "policyVersion": "v2", "runId": "ds-20260211T154144Z-814aa2e321"}, {"engineId": 10, "t": 20, "rul": 6.56, "anomRaw": 1e-06, "anomSmooth": 0.01614, "anomState": "OFF", "label": "Planned Maintenance", "reasonCodes": "RUL_LOW|ANOM_OFF", "reasonText": "RUL <= theta; planlı bakım penceresine girildi.", "action": "Planlı bakım/inspection", "theta": 30.0, "alphaHigh": 0.2692, "alphaLow": 0.2423, "policyVersion": "v2", "runId": "ds-20260211T154144Z-814aa2e321"}, {"engineId": 10, "t": 21, "rul": 2.59, "anomRaw": 5.7e-05, "anomSmooth": 0.012119, "anomState": "OFF", "label": "Planned Maintenance", "reasonCodes": "RUL_LOW|ANOM_OFF", "reasonText": "RUL <= theta; planlı bakım penceresine girildi.", "action": "Planlı bakım/inspection", "theta": 30.0, "alphaHigh": 0.2692, "alphaLow": 0.2423, "policyVersion": "v2", "runId": "ds-20260211T154144Z-814aa2e321"}, {"engineId": 10, "t": 22, "rul": 27.91, "anomRaw": 0.0, "anomSmooth": 0.00909, "anomState": "OFF", "label": "Planned Maintenance", "reasonCodes": "RUL_LOW|ANOM_OFF", "reasonText": "RUL <= theta; planlı bakım penceresine girildi.", "action": "Planlı bakım/inspection", "theta": 30.0, "alphaHigh": 0.2692, "alphaLow": 0.2423, "policyVersion": "v2", "runId": "ds-20260211T154144Z-814aa2e321"}, {"engineId": 10, "t": 23, "rul": 3.33, "anomRaw": 0.019064, "anomSmooth": 0.011583, "anomState": "OFF", "label": "Planned Maintenance", "reasonCodes": "RUL_LOW|ANOM_OFF", "reasonText": "RUL <= theta; planlı bakım penceresine girildi.", "action": "Planlı bakım/inspection", "theta": 30.0, "alphaHigh": 0.2692, "alphaLow": 0.2423, "policyVersion": "v2", "runId": "ds-20260211T154144Z-814aa2e321"}, {"engineId": 10, "t": 24, "rul": 0.0, "anomRaw": 0.0, "anomSmooth": 0.008688, "anomState": "OFF", "label": "Planned Maintenance", "reasonCodes": "RUL_LOW|ANOM_OFF", "reasonText": "RUL <= theta; planlı bakım penceresine girildi.", "action": "Planlı bakım/inspection", "theta": 30.0, "alphaHigh": 0.2692, "alphaLow": 0.2423, "policyVersion": "v2", "runId": "ds-20260211T154144Z-814aa2e321"}, {"engineId": 10, "t": 25, "rul": 31.65, "anomRaw": 0.019485, "anomSmooth": 0.011387, "anomState": "OFF", "label": "Normal Operation", "reasonCodes": "RUL_HIGH|ANOM_OFF", "reasonText": "RUL > theta ve anomaly_state OFF; rutin operasyon devam.", "action": "Rutin izleme", "theta": 30.0, "alphaHigh": 0.2692, "alphaLow": 0.2423, "policyVersion": "v2", "runId": "ds-20260211T154144Z-814aa2e321"}, {"engineId": 10, "t": 26, "rul": 0.0, "anomRaw": 0.0, "anomSmooth": 0.00854, "anomState": "OFF", "label": "Planned Maintenance", "reasonCodes": "RUL_LOW|ANOM_OFF", "reasonText": "RUL <= theta; planlı bakım penceresine girildi.", "action": "Planlı bakım/inspection", "theta": 30.0, "alphaHigh": 0.2692, "alphaLow": 0.2423, "policyVersion": "v2", "runId": "ds-20260211T154144Z-814aa2e321"}, {"engineId": 10, "t": 27, "rul": 21.43, "anomRaw": 2e-06, "anomSmooth": 0.006406, "anomState": "OFF", "label": "Planned Maintenance", "reasonCodes": "RUL_LOW|ANOM_OFF", "reasonText": "RUL <= theta; planlı bakım penceresine girildi.", "action": "Planlı bakım/inspection", "theta": 30.0, "alphaHigh": 0.2692, "alphaLow": 0.2423, "policyVersion": "v2", "runId": "ds-20260211T154144Z-814aa2e321"}, {"engineId": 10, "t": 28, "rul": 1.48, "anomRaw": 9.4e-05, "anomSmooth": 0.004828, "anomState": "OFF", "label": "Planned Maintenance", "reasonCodes": "RUL_LOW|ANOM_OFF", "reasonText": "RUL <= theta; planlı bakım penceresine girildi.", "action": "Planlı bakım/inspection", "theta": 30.0, "alphaHigh": 0.2692, "alphaLow": 0.2423, "policyVersion": "v2", "runId": "ds-20260211T154144Z-814aa2e321"}, {"engineId": 10, "t": 29, "rul": 26.42, "anomRaw": 0.0, "anomSmooth": 0.003621, "anomState": "OFF", "label": "Planned Maintenance", "reasonCodes": "RUL_LOW|ANOM_OFF", "reasonText": "RUL <= theta; planlı bakım penceresine girildi.", "action": "Planlı bakım/inspection", "theta": 30.0, "alphaHigh": 0.2692, "alphaLow": 0.2423, "policyVersion": "v2", "runId": "ds-20260211T154144Z-814aa2e321"}, {"engineId": 10, "t": 30, "rul": 4.61, "anomRaw": 0.031225, "anomSmooth": 0.010522, "anomState": "OFF", "label": "Planned Maintenance", "reasonCodes": "RUL_LOW|ANOM_OFF", "reasonText": "RUL <= theta; planlı bakım penceresine girildi.", "action": "Planlı bakım/inspection", "theta": 30.0, "alphaHigh": 0.2692, "alphaLow": 0.2423, "policyVersion": "v2", "runId": "ds-20260211T154144Z-814aa2e321"}, {"engineId": 10, "t": 31, "rul": 0.0, "anomRaw": 0.002668, "anomSmooth": 0.008558, "anomState": "OFF", "label": "Planned Maintenance", "reasonCodes": "RUL_LOW|ANOM_OFF", "reasonText": "RUL <= theta; planlı bakım penceresine girildi.", "action": "Planlı bakım/inspection", "theta": 30.0, "alphaHigh": 0.2692, "alphaLow": 0.2423, "policyVersion": "v2", "runId": "ds-20260211T154144Z-814aa2e321"}, {"engineId": 10, "t": 32, "rul": 0.56, "anomRaw": 0.007483, "anomSmooth": 0.00829, "anomState": "OFF", "label": "Planned Maintenance", "reasonCodes": "RUL_LOW|ANOM_OFF", "reasonText": "RUL <= theta; planlı bakım penceresine girildi.", "action": "Planlı bakım/inspection", "theta": 30.0, "alphaHigh": 0.2692, "alphaLow": 0.2423, "policyVersion": "v2", "runId": "ds-20260211T154144Z-814aa2e321"}, {"engineId": 10, "t": 33, "rul": 24.97, "anomRaw": 0.0, "anomSmooth": 0.006217, "anomState": "OFF", "label": "Planned Maintenance", "reasonCodes": "RUL_LOW|ANOM_OFF", "reasonText": "RUL <= theta; planlı bakım penceresine girildi.", "action": "Planlı bakım/inspection", "theta": 30.0, "alphaHigh": 0.2692, "alphaLow": 0.2423, "policyVersion": "v2", "runId": "ds-20260211T154144Z-814aa2e321"}, {"engineId": 10, "t": 34, "rul": 0.0, "anomRaw": 2.4e-05, "anomSmooth": 0.004669, "anomState": "OFF", "label": "Planned Maintenance", "reasonCodes": "RUL_LOW|ANOM_OFF", "reasonText": "RUL <= theta; planlı bakım penceresine girildi.", "action": "Planlı bakım/inspection", "theta": 30.0, "alphaHigh": 0.2692, "alphaLow": 0.2423, "policyVersion": "v2", "runId": "ds-20260211T154144Z-814aa2e321"}, {"engineId": 10, "t": 35, "rul": 6.68, "anomRaw": 0.991481, "anomSmooth": 0.251372, "anomState": "OFF", "label": "Planned Maintenance", "reasonCodes": "RUL_LOW|ANOM_OFF", "reasonText": "RUL <= theta; planlı bakım penceresine girildi.", "action": "Planlı bakım/inspection", "theta": 30.0, "alphaHigh": 0.2692, "alphaLow": 0.2423, "policyVersion": "v2", "runId": "ds-20260211T154144Z-814aa2e321"}, {"engineId": 10, "t": 36, "rul": 0.0, "anomRaw": 0.008522, "anomSmooth": 0.19066, "anomState": "OFF", "label": "Planned Maintenance", "reasonCodes": "RUL_LOW|ANOM_OFF", "reasonText": "RUL <= theta; planlı bakım penceresine girildi.", "action": "Planlı bakım/inspection", "theta": 30.0, "alphaHigh": 0.2692, "alphaLow": 0.2423, "policyVersion": "v2", "runId": "ds-20260211T154144Z-814aa2e321"}, {"engineId": 10, "t": 37, "rul": 47.66, "anomRaw": 0.0, "anomSmooth": 0.142995, "anomState": "OFF", "label": "Normal Operation", "reasonCodes": "RUL_HIGH|ANOM_OFF", "reasonText": "RUL > theta ve anomaly_state OFF; rutin operasyon devam.", "action": "Rutin izleme", "theta": 30.0, "alphaHigh": 0.2692, "alphaLow": 0.2423, "policyVersion": "v2", "runId": "ds-20260211T154144Z-814aa2e321"}, {"engineId": 10, "t": 38, "rul": 0.0, "anomRaw": 0.006291, "anomSmooth": 0.108819, "anomState": "OFF", "label": "Planned Maintenance", "reasonCodes": "RUL_LOW|ANOM_OFF", "reasonText": "RUL <= theta; planlı bakım penceresine girildi.", "action": "Planlı bakım/inspection", "theta": 30.0, "alphaHigh": 0.2692, "alphaLow": 0.2423, "policyVersion": "v2", "runId": "ds-20260211T154144Z-814aa2e321"}, {"engineId": 10, "t": 39, "rul": 0.0, "anomRaw": 0.032914, "anomSmooth": 0.089843, "anomState": "OFF", "label": "Planned Maintenance", "reasonCodes": "RUL_LOW|ANOM_OFF", "reasonText": "RUL <= theta; planlı bakım penceresine girildi.", "action": "Planlı bakım/inspection", "theta": 30.0, "alphaHigh": 0.2692, "alphaLow": 0.2423, "policyVersion": "v2", "runId": "ds-20260211T154144Z-814aa2e321"}, {"engineId": 10, "t": 40, "rul": 0.0, "anomRaw": 1e-06, "anomSmooth": 0.067382, "anomState": "OFF", "label": "Planned Maintenance", "reasonCodes": "RUL_LOW|ANOM_OFF", "reasonText": "RUL <= theta; planlı bakım penceresine girildi.", "action": "Planlı bakım/inspection", "theta": 30.0, "alphaHigh": 0.2692, "alphaLow": 0.2423, "policyVersion": "v2", "runId": "ds-20260211T154144Z-814aa2e321"}, {"engineId": 10, "t": 41, "rul": 0.0, "anomRaw": 0.000117, "anomSmooth": 0.050566, "anomState": "OFF", "label": "Planned Maintenance", "reasonCodes": "RUL_LOW|ANOM_OFF", "reasonText": "RUL <= theta; planlı bakım penceresine girildi.", "action": "Planlı bakım/inspection", "theta": 30.0, "alphaHigh": 0.2692, "alphaLow": 0.2423, "policyVersion": "v2", "runId": "ds-20260211T154144Z-814aa2e321"}, {"engineId": 10, "t": 42, "rul": 0.0, "anomRaw": 0.129272, "anomSmooth": 0.070242, "anomState": "OFF", "label": "Planned Maintenance", "reasonCodes": "RUL_LOW|ANOM_OFF", "reasonText": "RUL <= theta; planlı bakım penceresine girildi.", "action": "Planlı bakım/inspection", "theta": 30.0, "alphaHigh": 0.2692, "alphaLow": 0.2423, "policyVersion": "v2", "runId": "ds-20260211T154144Z-814aa2e321"}, {"engineId": 10, "t": 43, "rul": 0.0, "anomRaw": 0.0, "anomSmooth": 0.052682, "anomState": "OFF", "label": "Planned Maintenance", "reasonCodes": "RUL_LOW|ANOM_OFF", "reasonText": "RUL <= theta; planlı bakım penceresine girildi.", "action": "Planlı bakım/inspection", "theta": 30.0, "alphaHigh": 0.2692, "alphaLow": 0.2423, "policyVersion": "v2", "runId": "ds-20260211T154144Z-814aa2e321"}, {"engineId": 10, "t": 44, "rul": 9.62, "anomRaw": 0.031491, "anomSmooth": 0.047384, "anomState": "OFF", "label": "Planned Maintenance", "reasonCodes": "RUL_LOW|ANOM_OFF", "reasonText": "RUL <= theta; planlı bakım penceresine girildi.", "action": "Planlı bakım/inspection", "theta": 30.0, "alphaHigh": 0.2692, "alphaLow": 0.2423, "policyVersion": "v2", "runId": "ds-20260211T154144Z-814aa2e321"}, {"engineId": 10, "t": 45, "rul": 27.11, "anomRaw": 0.0, "anomSmooth": 0.035538, "anomState": "OFF", "label": "Planned Maintenance", "reasonCodes": "RUL_LOW|ANOM_OFF", "reasonText": "RUL <= theta; planlı bakım penceresine girildi.", "action": "Planlı bakım/inspection", "theta": 30.0, "alphaHigh": 0.2692, "alphaLow": 0.2423, "policyVersion": "v2", "runId": "ds-20260211T154144Z-814aa2e321"}, {"engineId": 10, "t": 46, "rul": 3.5, "anomRaw": 0.0, "anomSmooth": 0.026654, "anomState": "OFF", "label": "Planned Maintenance", "reasonCodes": "RUL_LOW|ANOM_OFF", "reasonText": "RUL <= theta; planlı bakım penceresine girildi.", "action": "Planlı bakım/inspection", "theta": 30.0, "alphaHigh": 0.2692, "alphaLow": 0.2423, "policyVersion": "v2", "runId": "ds-20260211T154144Z-814aa2e321"}, {"engineId": 10, "t": 47, "rul": 0.02, "anomRaw": 1e-06, "anomSmooth": 0.01999, "anomState": "OFF", "label": "Planned Maintenance", "reasonCodes": "RUL_LOW|ANOM_OFF", "reasonText": "RUL <= theta; planlı bakım penceresine girildi.", "action": "Planlı bakım/inspection", "theta": 30.0, "alphaHigh": 0.2692, "alphaLow": 0.2423, "policyVersion": "v2", "runId": "ds-20260211T154144Z-814aa2e321"}, {"engineId": 10, "t": 48, "rul": 0.0, "anomRaw": 1.8e-05, "anomSmooth": 0.014997, "anomState": "OFF", "label": "Planned Maintenance", "reasonCodes": "RUL_LOW|ANOM_OFF", "reasonText": "RUL <= theta; planlı bakım penceresine girildi.", "action": "Planlı bakım/inspection", "theta": 30.0, "alphaHigh": 0.2692, "alphaLow": 0.2423, "policyVersion": "v2", "runId": "ds-20260211T154144Z-814aa2e321"}, {"engineId": 10, "t": 49, "rul": 0.0, "anomRaw": 0.0, "anomSmooth": 0.011248, "anomState": "OFF", "label": "Planned Maintenance", "reasonCodes": "RUL_LOW|ANOM_OFF", "reasonText": "RUL <= theta; planlı bakım penceresine girildi.", "action": "Planlı bakım/inspection", "theta": 30.0, "alphaHigh": 0.2692, "alphaLow": 0.2423, "policyVersion": "v2", "runId": "ds-20260211T154144Z-814aa2e321"}, {"engineId": 10, "t": 50, "rul": 1.65, "anomRaw": 0.00775, "anomSmooth": 0.010374, "anomState": "OFF", "label": "Planned Maintenance", "reasonCodes": "RUL_LOW|ANOM_OFF", "reasonText": "RUL <= theta; planlı bakım penceresine girildi.", "action": "Planlı bakım/inspection", "theta": 30.0, "alphaHigh": 0.2692, "alphaLow": 0.2423, "policyVersion": "v2", "runId": "ds-20260211T154144Z-814aa2e321"}, {"engineId": 10, "t": 51, "rul": 18.34, "anomRaw": 0.0, "anomSmooth": 0.00778, "anomState": "OFF", "label": "Planned Maintenance", "reasonCodes": "RUL_LOW|ANOM_OFF", "reasonText": "RUL <= theta; planlı bakım penceresine girildi.", "action": "Planlı bakım/inspection", "theta": 30.0, "alphaHigh": 0.2692, "alphaLow": 0.2423, "policyVersion": "v2", "runId": "ds-20260211T154144Z-814aa2e321"}, {"engineId": 10, "t": 52, "rul": 0.0, "anomRaw": 0.000542, "anomSmooth": 0.005971, "anomState": "OFF", "label": "Planned Maintenance", "reasonCodes": "RUL_LOW|ANOM_OFF", "reasonText": "RUL <= theta; planlı bakım penceresine girildi.", "action": "Planlı bakım/inspection", "theta": 30.0, "alphaHigh": 0.2692, "alphaLow": 0.2423, "policyVersion": "v2", "runId": "ds-20260211T154144Z-814aa2e321"}, {"engineId": 10, "t": 53, "rul": 0.0, "anomRaw": 0.001851, "anomSmooth": 0.004941, "anomState": "OFF", "label": "Planned Maintenance", "reasonCodes": "RUL_LOW|ANOM_OFF", "reasonText": "RUL <= theta; planlı bakım penceresine girildi.", "action": "Planlı bakım/inspection", "theta": 30.0, "alphaHigh": 0.2692, "alphaLow": 0.2423, "policyVersion": "v2", "runId": "ds-20260211T154144Z-814aa2e321"}, {"engineId": 10, "t": 54, "rul": 0.0, "anomRaw": 0.0, "anomSmooth": 0.003706, "anomState": "OFF", "label": "Planned Maintenance", "reasonCodes": "RUL_LOW|ANOM_OFF", "reasonText": "RUL <= theta; planlı bakım penceresine girildi.", "action": "Planlı bakım/inspection", "theta": 30.0, "alphaHigh": 0.2692, "alphaLow": 0.2423, "policyVersion": "v2", "runId": "ds-20260211T154144Z-814aa2e321"}, {"engineId": 10, "t": 55, "rul": 0.0, "anomRaw": 0.001, "anomSmooth": 0.003029, "anomState": "OFF", "label": "Planned Maintenance", "reasonCodes": "RUL_LOW|ANOM_OFF", "reasonText": "RUL <= theta; planlı bakım penceresine girildi.", "action": "Planlı bakım/inspection", "theta": 30.0, "alphaHigh": 0.2692, "alphaLow": 0.2423, "policyVersion": "v2", "runId": "ds-20260211T154144Z-814aa2e321"}, {"engineId": 10, "t": 56, "rul": 0.0, "anomRaw": 0.014246, "anomSmooth": 0.005833, "anomState": "OFF", "label": "Planned Maintenance", "reasonCodes": "RUL_LOW|ANOM_OFF", "reasonText": "RUL <= theta; planlı bakım penceresine girildi.", "action": "Planlı bakım/inspection", "theta": 30.0, "alphaHigh": 0.2692, "alphaLow": 0.2423, "policyVersion": "v2", "runId": "ds-20260211T154144Z-814aa2e321"}, {"engineId": 10, "t": 57, "rul": 0.0, "anomRaw": 0.013617, "anomSmooth": 0.007779, "anomState": "OFF", "label": "Planned Maintenance", "reasonCodes": "RUL_LOW|ANOM_OFF", "reasonText": "RUL <= theta; planlı bakım penceresine girildi.", "action": "Planlı bakım/inspection", "theta": 30.0, "alphaHigh": 0.2692, "alphaLow": 0.2423, "policyVersion": "v2", "runId": "ds-20260211T154144Z-814aa2e321"}, {"engineId": 10, "t": 58, "rul": 0.0, "anomRaw": 0.009122, "anomSmooth": 0.008115, "anomState": "OFF", "label": "Planned Maintenance", "reasonCodes": "RUL_LOW|ANOM_OFF", "reasonText": "RUL <= theta; planlı bakım penceresine girildi.", "action": "Planlı bakım/inspection", "theta": 30.0, "alphaHigh": 0.2692, "alphaLow": 0.2423, "policyVersion": "v2", "runId": "ds-20260211T154144Z-814aa2e321"}, {"engineId": 10, "t": 59, "rul": 0.0, "anomRaw": 0.028497, "anomSmooth": 0.013211, "anomState": "OFF", "label": "Planned Maintenance", "reasonCodes": "RUL_LOW|ANOM_OFF", "reasonText": "RUL <= theta; planlı bakım penceresine girildi.", "action": "Planlı bakım/inspection", "theta": 30.0, "alphaHigh": 0.2692, "alphaLow": 0.2423, "policyVersion": "v2", "runId": "ds-20260211T154144Z-814aa2e321"}, {"engineId": 10, "t": 60, "rul": 0.0, "anomRaw": 0.838836, "anomSmooth": 0.219617, "anomState": "OFF", "label": "Planned Maintenance", "reasonCodes": "RUL_LOW|ANOM_OFF", "reasonText": "RUL <= theta; planlı bakım penceresine girildi.", "action": "Planlı bakım/inspection", "theta": 30.0, "alphaHigh": 0.2692, "alphaLow": 0.2423, "policyVersion": "v2", "runId": "ds-20260211T154144Z-814aa2e321"}, {"engineId": 10, "t": 61, "rul": 13.33, "anomRaw": 0.195847, "anomSmooth": 0.213674, "anomState": "OFF", "label": "Planned Maintenance", "reasonCodes": "RUL_LOW|ANOM_OFF", "reasonText": "RUL <= theta; planlı bakım penceresine girildi.", "action": "Planlı bakım/inspection", "theta": 30.0, "alphaHigh": 0.2692, "alphaLow": 0.2423, "policyVersion": "v2", "runId": "ds-20260211T154144Z-814aa2e321"}, {"engineId": 10, "t": 62, "rul": 0.0, "anomRaw": 0.398837, "anomSmooth": 0.259965, "anomState": "OFF", "label": "Planned Maintenance", "reasonCodes": "RUL_LOW|ANOM_OFF", "reasonText": "RUL <= theta; planlı bakım penceresine girildi.", "action": "Planlı bakım/inspection", "theta": 30.0, "alphaHigh": 0.2692, "alphaLow": 0.2423, "policyVersion": "v2", "runId": "ds-20260211T154144Z-814aa2e321"}, {"engineId": 10, "t": 63, "rul": 8.04, "anomRaw": 0.827349, "anomSmooth": 0.401811, "anomState": "OFF", "label": "Planned Maintenance", "reasonCodes": "RUL_LOW|ANOM_OFF|PERSISTENCE_PENDING", "reasonText": "RUL <= theta; planlı bakım penceresine girildi. ON için 3 ardışık cycle şartı henüz tamamlanmadı.", "action": "Planlı bakım/inspection", "theta": 30.0, "alphaHigh": 0.2692, "alphaLow": 0.2423, "policyVersion": "v2", "runId": "ds-20260211T154144Z-814aa2e321"}, {"engineId": 10, "t": 64, "rul": 0.0, "anomRaw": 0.715711, "anomSmooth": 0.480286, "anomState": "OFF", "label": "Planned Maintenance", "reasonCodes": "RUL_LOW|ANOM_OFF|PERSISTENCE_PENDING", "reasonText": "RUL <= theta; planlı bakım penceresine girildi. ON için 3 ardışık cycle şartı henüz tamamlanmadı.", "action": "Planlı bakım/inspection", "theta": 30.0, "alphaHigh": 0.2692, "alphaLow": 0.2423, "policyVersion": "v2", "runId": "ds-20260211T154144Z-814aa2e321"}, {"engineId": 10, "t": 65, "rul": 0.0, "anomRaw": 0.980747, "anomSmooth": 0.605401, "anomState": "ON", "label": "Immediate Maintenance", "reasonCodes": "RUL_LOW|ANOM_ON|STATE_CHANGE_OFF_TO_ON", "reasonText": "RUL <= theta ve anomaly_state ON; acil bakım değerlendirmesi gerekli.", "action": "Acil bakım kararı için yükselt", "theta": 30.0, "alphaHigh": 0.2692, "alphaLow": 0.2423, "policyVersion": "v2", "runId": "ds-20260211T154144Z-814aa2e321"}, {"engineId": 10, "t": 66, "rul": 0.0, "anomRaw": 0.755378, "anomSmooth": 0.642895, "anomState": "ON", "label": "Immediate Maintenance", "reasonCodes": "RUL_LOW|ANOM_ON", "reasonText": "RUL <= theta ve anomaly_state ON; acil bakım değerlendirmesi gerekli.", "action": "Acil bakım kararı için yükselt", "theta": 30.0, "alphaHigh": 0.2692, "alphaLow": 0.2423, "policyVersion": "v2", "runId": "ds-20260211T154144Z-814aa2e321"}]